faiss/__init__.py
faiss/_swigfaiss.abi3.so
faiss/array_conversions.py
faiss/class_wrappers.py
faiss/contrib/__init__.py
faiss/contrib/big_batch_search.py
faiss/contrib/client_server.py
faiss/contrib/clustering.py
faiss/contrib/datasets.py
faiss/contrib/evaluation.py
faiss/contrib/exhaustive_search.py
faiss/contrib/factory_tools.py
faiss/contrib/inspect_tools.py
faiss/contrib/ivf_tools.py
faiss/contrib/ondisk.py
faiss/contrib/rpc.py
faiss/contrib/torch/__init__.py
faiss/contrib/torch/clustering.py
faiss/contrib/torch/quantization.py
faiss/contrib/torch_utils.py
faiss/contrib/vecs_io.py
faiss/extra_wrappers.py
faiss/gpu_wrappers.py
faiss/loader.py
faiss/swigfaiss.py
rf_faiss_gpu-1.12.0.dist-info/METADATA
rf_faiss_gpu-1.12.0.dist-info/WHEEL
rf_faiss_gpu-1.12.0.dist-info/licenses/LICENSE
rf_faiss_gpu-1.12.0.dist-info/licenses/NOTICE
rf_faiss_gpu-1.12.0.dist-info/RECORD
