Metadata-Version: 2.4
Name: rf-faiss-gpu
Version: 1.12.0
Summary: A library for efficient similarity search and clustering of dense vectors.
Keywords: faiss,similarity search,clustering,machine learning
Author-Email: Kota Yamaguchi <yamaguchi_kota@cyberagent.co.jp>
License-Expression: MIT AND BSD-3-Clause
Classifier: Development Status :: 4 - Beta
Classifier: Intended Audience :: Developers
Classifier: Intended Audience :: Science/Research
Classifier: Operating System :: MacOS :: MacOS X
Classifier: Operating System :: Microsoft :: Windows
Classifier: Operating System :: POSIX
Classifier: Programming Language :: Python :: 3.9
Classifier: Programming Language :: Python :: 3.10
Classifier: Programming Language :: Python :: 3.11
Classifier: Programming Language :: Python :: 3.12
Classifier: Programming Language :: Python :: 3.13
Classifier: Programming Language :: Python :: 3.14
Classifier: Topic :: Scientific/Engineering :: Artificial Intelligence
Project-URL: Repository, https://github.com/kyamagu/faiss-wheels
Requires-Python: <3.15,>=3.9
Requires-Dist: numpy<3.0,>=1.25.0
Requires-Dist: packaging
